flask_fontawesome_headers.py
Flask_FontAwesome_Headers-0.1.0.dist-info/RECORD
Flask_FontAwesome_Headers-0.1.0.dist-info/DESCRIPTION.rst
Flask_FontAwesome_Headers-0.1.0.dist-info/top_level.txt
Flask_FontAwesome_Headers-0.1.0.dist-info/METADATA
Flask_FontAwesome_Headers-0.1.0.dist-info/WHEEL
Flask_FontAwesome_Headers-0.1.0.dist-info/metadata.json
