Metadata-Version: 2.0
Name: Flask-FontAwesome-Headers
Version: 0.1.0
Summary: Sets CORS HTTP response headers for Font-Awesome files served by Flask's send_file().
Home-page: https://github.com/Jaza/flask-fontawesome-headers
Author: Jeremy Epstein
Author-email: jazepstein@gmail.com
License: UNKNOWN
Platform: any
Classifier: Development Status :: 2 - Pre-Alpha
Classifier: Environment :: Web Environment
Classifier: Intended Audience :: Developers
Classifier: Operating System :: OS Independent
Classifier: Programming Language :: Python
Classifier: Programming Language :: Python :: 2
Classifier: Programming Language :: Python :: 2.7
Classifier: Programming Language :: Python :: 3
Classifier: Programming Language :: Python :: 3.3
Requires-Dist: Flask
